{
    "analysis_settings": {
        "window_start_month": 13,
        "window_end_month": 36
    },
    "base_loan": {
        "principal": 425000,
        "start_rate": 4.3,
        "years": 30
    },
    "rate_changes": [
        {
            "month": 13,
            "new_rate": [
                3.3,
                2.1
            ]
        },
        {
            "month": 25,
            "new_rate": [
                2.8,
                2.2
            ]
        },
        {
            "month": 37,
            "new_rate": 3.6
        }
    ],
    "overpayments": [
        {
            "month": 13,
            "amount": 1800
        }
    ]
}